{
    "eventid": "199306060003",
    "iyear": "1993",
    "imonth": "6",
    "iday": "6",
    "extended": "0",
    "country": "209",
    "country_txt": "Turkey",
    "region": "10",
    "region_txt": "Middle East & North Africa",
    "provstate": "Batman (Province)",
    "city": "Dortboluk",
    "vicinity": "0",
    "summary": "06/06/1993: Suspected PKK members attacked in Dortboluk, a village located in the township of Sason in southeastern Turkey. Five died and two were wounded.",
    "crit1": "1",
    "crit2": "1",
    "crit3": "1",
    "doubtterr": "0",
    "multiple": "0",
    "success": "1",
    "suicide": "0",
    "attacktype1": "2",
    "attacktype1_txt": "Armed Assault",
    "targtype1": "14",
    "targtype1_txt": "Private Citizens & Property",
    "corp1": "Turkish Civilians",
    "target1": "Villagers in Dortboluk",
    "natlty1": "209",
    "natlty1_txt": "Turkey",
    "gname": "Kurdistan Workers' Party (PKK)",
    "motive": "Unknown",
    "guncertain1": "1",
    "individual": "0",
    "claimed": "0",
    "compclaim": "-9",
    "weaptype1": "5",
    "weaptype1_txt": "Firearms",
    "weapsubtype1": "5",
    "weapsubtype1_txt": "Unknown Gun Type",
    "nkill": "5",
    "nkillus": "0",
    "nkillter": "1",
    "nwound": "2",
    "nwoundus": "0",
    "nwoundte": "0",
    "property": "0",
    "ishostkid": "0",
    "scite1": "“Four villagers, one Kurdish rebel killed,” Xinhua General Overseas News Service, June 7, 1993.",
    "scite2": "“300 slain in 2 weeks in Kurdish part of Turkey,” Chicago Tribune, June 8, 1993.",
    "dbsource": "CETIS",
    "INT_LOG": "0",
    "INT_IDEO": "0",
    "INT_MISC": "0",
    "INT_ANY": "0"
}