{
    "eventid": "199306240013",
    "iyear": "1993",
    "imonth": "6",
    "iday": "24",
    "extended": "0",
    "country": "75",
    "country_txt": "Germany",
    "region": "8",
    "region_txt": "Western Europe",
    "provstate": "North Rhine-Westphalia (State)",
    "city": "Dortmund",
    "vicinity": "0",
    "summary": "06/24/1993: In a series of related attacks, ten Kurdistan Workers' Party (PKK) members attacked the Turkish Pamuk Bank causing extensive damage. No injuries were reported.",
    "crit1": "1",
    "crit2": "1",
    "crit3": "1",
    "doubtterr": "0",
    "multiple": "1",
    "success": "1",
    "suicide": "0",
    "attacktype1": "7",
    "attacktype1_txt": "Facility/Infrastructure Attack",
    "targtype1": "1",
    "targtype1_txt": "Business",
    "corp1": "Turkish Pamuk Bank",
    "target1": "Turkish Pamuk Bank in Dortmund",
    "natlty1": "209",
    "natlty1_txt": "Turkey",
    "gname": "Kurdistan Workers' Party (PKK)",
    "motive": "Protesting Turkish treatment of Kurds",
    "guncertain1": "0",
    "individual": "0",
    "nperps": "10",
    "claimed": "0",
    "compclaim": "-9",
    "weaptype1": "13",
    "weaptype1_txt": "Unknown",
    "nkill": "0",
    "nkillus": "0",
    "nkillter": "0",
    "nwound": "0",
    "nwoundus": "0",
    "nwoundte": "0",
    "property": "1",
    "propextent": "4",
    "propextent_txt": "Unknown",
    "ishostkid": "0",
    "addnotes": "This was one of seventeen related attacks (cf. 199306240001-4; 199306240006-16; 199306240019-20).",
    "scite1": "Edward F. Mickolus, Terrorism, 1992-1995: A Chronology of Events and a Selectively Annotated Bibliography, Westport, CT: Greenwood Press, 1997.",
    "dbsource": "CETIS",
    "INT_LOG": "1",
    "INT_IDEO": "0",
    "INT_MISC": "1",
    "INT_ANY": "1"
}