<Order>
  <RequiredDate>1996-08-28T17:12:34</RequiredDate>
  <ShipName>Romero y tomillo</ShipName>
  <OrderDetails>
    <OrderDetail>
      <UnitPrice>14.4000</UnitPrice>
      <Discount>0</Discount>
      <Quantity>4</Quantity>
      <ProductID>35</ProductID>
    </OrderDetail>
  </OrderDetails>
  <ShippedDate>1996-08-21T12:41:22</ShippedDate>
  <ShipCity>Madrid</ShipCity>
  <CustomerID>ROMEY</CustomerID>
  <ShipVia>1</ShipVia>
  <ShipPostalCode>28001</ShipPostalCode>
  <OrderID>10281</OrderID>
  <OrderDate>1996-08-14T17:20:11</OrderDate>
  <ShipRegion>null</ShipRegion>
  <ShipAddress>Gran Vía, 1</ShipAddress>
  <ShipCountry>Spain</ShipCountry>
  <EmployeeID>4</EmployeeID>
  <Freight>2.9400</Freight>
</Order>
