<Order>
  <RequiredDate>1997-01-09T03:02:41</RequiredDate>
  <ShipName>Hungry Owl All-Night Grocers</ShipName>
  <OrderDetails>
    <OrderDetail>
      <UnitPrice>12.0000</UnitPrice>
      <Discount>0</Discount>
      <Quantity>30</Quantity>
      <ProductID>70</ProductID>
    </OrderDetail>
  </OrderDetails>
  <ShippedDate>1997-01-16T19:33:23</ShippedDate>
  <ShipCity>Cork</ShipCity>
  <CustomerID>HUNGO</CustomerID>
  <ShipVia>3</ShipVia>
  <ShipPostalCode>null</ShipPostalCode>
  <OrderID>10380</OrderID>
  <OrderDate>1996-12-12T13:58:11</OrderDate>
  <ShipRegion>Co. Cork</ShipRegion>
  <ShipAddress>8 Johnstown Road</ShipAddress>
  <ShipCountry>Ireland</ShipCountry>
  <EmployeeID>8</EmployeeID>
  <Freight>35.0300</Freight>
</Order>
