<Order>
  <RequiredDate>1997-01-14T11:04:14</RequiredDate>
  <ShipName>Vaffeljernet</ShipName>
  <OrderDetails>
    <OrderDetail>
      <UnitPrice>10.4000</UnitPrice>
      <Discount>0</Discount>
      <Quantity>14</Quantity>
      <ProductID>77</ProductID>
    </OrderDetail>
  </OrderDetails>
  <ShippedDate>1997-01-08T10:57:55</ShippedDate>
  <ShipCity>Århus</ShipCity>
  <CustomerID>VAFFE</CustomerID>
  <ShipVia>3</ShipVia>
  <ShipPostalCode>8200</ShipPostalCode>
  <OrderID>10399</OrderID>
  <OrderDate>1996-12-31T00:19:18</OrderDate>
  <ShipRegion>null</ShipRegion>
  <ShipAddress>Smagsloget 45</ShipAddress>
  <ShipCountry>Denmark</ShipCountry>
  <EmployeeID>8</EmployeeID>
  <Freight>27.3600</Freight>
</Order>
