<Order>
  <RequiredDate>1997-08-07T21:25:25</RequiredDate>
  <ShipName>Ernst Handel</ShipName>
  <OrderDetails>
    <OrderDetail>
      <UnitPrice>36.0000</UnitPrice>
      <Discount>0.25</Discount>
      <Quantity>65</Quantity>
      <ProductID>69</ProductID>
    </OrderDetail>
  </OrderDetails>
  <ShippedDate>1997-07-14T08:26:16</ShippedDate>
  <ShipCity>Graz</ShipCity>
  <CustomerID>ERNSH</CustomerID>
  <ShipVia>1</ShipVia>
  <ShipPostalCode>8010</ShipPostalCode>
  <OrderID>10595</OrderID>
  <OrderDate>1997-07-10T23:24:29</OrderDate>
  <ShipRegion>null</ShipRegion>
  <ShipAddress>Kirchgasse 6</ShipAddress>
  <ShipCountry>Austria</ShipCountry>
  <EmployeeID>2</EmployeeID>
  <Freight>96.7800</Freight>
</Order>
