<Order>
  <RequiredDate>1997-09-01T04:57:27</RequiredDate>
  <ShipName>Mère Paillarde</ShipName>
  <OrderDetails>
    <OrderDetail>
      <UnitPrice>21.0000</UnitPrice>
      <Discount>0</Discount>
      <Quantity>40</Quantity>
      <ProductID>22</ProductID>
    </OrderDetail>
  </OrderDetails>
  <ShippedDate>1997-08-07T21:09:20</ShippedDate>
  <ShipCity>Montréal</ShipCity>
  <CustomerID>MEREP</CustomerID>
  <ShipVia>3</ShipVia>
  <ShipPostalCode>H1J 1C3</ShipPostalCode>
  <OrderID>10619</OrderID>
  <OrderDate>1997-08-04T13:36:40</OrderDate>
  <ShipRegion>Québec</ShipRegion>
  <ShipAddress>43 rue St. Laurent</ShipAddress>
  <ShipCountry>Canada</ShipCountry>
  <EmployeeID>3</EmployeeID>
  <Freight>91.0500</Freight>
</Order>
