<Order>
  <RequiredDate>1998-03-06T12:54:49</RequiredDate>
  <ShipName>Victuailles en stock</ShipName>
  <OrderDetails>
    <OrderDetail>
      <UnitPrice>15.0000</UnitPrice>
      <Discount>0.15</Discount>
      <Quantity>30</Quantity>
      <ProductID>70</ProductID>
    </OrderDetail>
  </OrderDetails>
  <ShippedDate>1998-01-30T04:41:41</ShippedDate>
  <ShipCity>Lyon</ShipCity>
  <CustomerID>VICTE</CustomerID>
  <ShipVia>1</ShipVia>
  <ShipPostalCode>69004</ShipPostalCode>
  <OrderID>10850</OrderID>
  <OrderDate>1998-01-23T01:57:38</OrderDate>
  <ShipRegion>null</ShipRegion>
  <ShipAddress>2, rue du Commerce</ShipAddress>
  <ShipCountry>France</ShipCountry>
  <EmployeeID>1</EmployeeID>
  <Freight>49.1900</Freight>
</Order>
