<Order>
  <RequiredDate>1998-04-28T20:16:24</RequiredDate>
  <ShipName>Rattlesnake Canyon Grocery</ShipName>
  <OrderDetails>
    <OrderDetail>
      <UnitPrice>49.3000</UnitPrice>
      <Discount>0.1</Discount>
      <Quantity>40</Quantity>
      <ProductID>62</ProductID>
    </OrderDetail>
  </OrderDetails>
  <ShippedDate>1998-04-10T18:12:25</ShippedDate>
  <ShipCity>Albuquerque</ShipCity>
  <CustomerID>RATTC</CustomerID>
  <ShipVia>2</ShipVia>
  <ShipPostalCode>87110</ShipPostalCode>
  <OrderID>10988</OrderID>
  <OrderDate>1998-03-31T22:10:13</OrderDate>
  <ShipRegion>NM</ShipRegion>
  <ShipAddress>2817 Milton Dr.</ShipAddress>
  <ShipCountry>USA</ShipCountry>
  <EmployeeID>3</EmployeeID>
  <Freight>61.1400</Freight>
</Order>
