<?xml version="1.0" encoding="UTF-8" standalone="yes"?>
<person>
  <personId>10063</personId>
  <nameGroup>
    <givenname>
      <value>Orville</value>
    </givenname>
    <surname>
      <value>Laurie</value>
    </surname>
    <fullname>
      <classification>U</classification>
      <restricted>false</restricted>
      <value>Laurie Orville</value>
      <source>
        <name>Los Angeles Times</name>
        <ts>2018-08-22T17:36:40Z</ts>
      </source>
    </fullname>
  </nameGroup>
  <emails>
    <email>
      <value>mgouldstraw0@bing.com</value>
      <classification>C</classification>
      <restricted>false</restricted>
    </email>
  </emails>
  <phone>713-658-0374</phone>
  <ssn>
    <value>382-76-9319</value>
    <restricted>true</restricted>
  </ssn>
  <images>
    <image>
      <url>https://cdn1.marklogic.com/wp-content/uploads/2020/11/george-bloom-headshot-300x300-1.jpg</url>
      <source>
        <name>Chicago Tribune</name>
        <ts>2011-10-20T14:30:20Z</ts>
        <uploadedBy>pbletso0</uploadedBy>
      </source>
    </image>
    <image>
      <url>https://cdn1.marklogic.com/wp-content/uploads/2018/01/Diane-Burley-MarkLogic-2015.jpg</url>
      <source>
        <name>New York Times</name>
        <ts>2019-07-31T17:11:16Z</ts>
        <uploadedBy>tfolger0</uploadedBy>
      </source>
    </image>
  </images>
  <addresses>
    <address>
      <street>16434 Mariners Cove Drive</street>
      <city>Washington</city>
      <state>DC</state>
      <postal>20046</postal>
      <country>United States</country>
      <latitude>38.8933</latitude>
      <longitude>-77.0146</longitude>
    </address>
  </addresses>
  <schools>
    <school>
      <country>United States</country>
      <name>Dominican College of San Rafael</name>
      <city>Vienna</city>
      <state>VA</state>
      <postal>22184</postal>
      <latitude>33.5177039</latitude>
      <longitude>-117.693138</longitude>
    </school>
    <school>
      <country>United States</country>
      <name>Miami Dade College</name>
      <city>Jacksonville</city>
      <state>FL</state>
      <postal>32277</postal>
      <latitude>30.3776024</latitude>
      <longitude>-81.5870604</longitude>
    </school>
  </schools>
  <status>Inactive</status>
  <sources>
    <source>
      <name>Los Angeles Times</name>
      <ts>2017-09-23T19:15:32Z</ts>
    </source>
  </sources>
  <sources>
    <source>
      <name>USA Today</name>
      <ts>2013-03-27T09:10:43Z</ts>
    </source>
  </sources>
  <sources>
    <source>
      <name>Chicago Tribune</name>
      <ts>2020-09-24T12:50:23Z</ts>
    </source>
  </sources>
  <relations>
    <relation>
      <id>10070</id>
      <predicate>worksWith</predicate>
      <imageSrc>https://cdn1.marklogic.com/wp-content/uploads/2018/01/Michael-Malgeri-MarkLogic.jpg</imageSrc>
      <fullname>Breitler Cacilie</fullname>
      <city>San Antonio</city>
      <state>TX</state>
    </relation>
    <relation>
      <id>10066</id>
      <predicate>relatedTo</predicate>
      <imageSrc>https://cdn1.marklogic.com/wp-content/uploads/2021/07/chuck-hollis.jpeg</imageSrc>
      <fullname>Karleman Emmet</fullname>
      <city>Reston</city>
      <state>VA</state>
    </relation>
    <relation>
      <id>10051</id>
      <predicate>worksWith</predicate>
      <imageSrc>https://cdn1.marklogic.com/wp-content/uploads/2021/02/1612313387205.jpeg</imageSrc>
      <fullname>Biswell Frederich</fullname>
      <city>Buffalo</city>
      <state>NY</state>
    </relation>
    <relation>
      <id>10031</id>
      <predicate>worksWith</predicate>
      <imageSrc>https://cdn1.marklogic.com/wp-content/uploads/2021/02/1612313387205.jpeg</imageSrc>
      <fullname>Taudevin Betti</fullname>
      <city>Sacramento</city>
      <state>CA</state>
    </relation>
    <relation>
      <id>10055</id>
      <predicate>livesWith</predicate>
      <imageSrc>https://cdn1.marklogic.com/wp-content/uploads/2021/02/1612313387205.jpeg</imageSrc>
      <fullname>Gallehawk Martin</fullname>
      <city>Salt Lake City</city>
      <state>UT</state>
    </relation>
  </relations>
  <createdOn>
    <ts>2022-02-02T13:42:07Z</ts>
    <user>olaurie1q</user>
  </createdOn>
  <lastUpdated>
    <ts>2022-01-01T08:42:13Z</ts>
    <user>olaurie1q</user>
  </lastUpdated>
  <socials>
    <social>
      <site>facebook</site>
      <handle>cbenedick0</handle>
      <address>http://vkontakte.ru/primis.png</address>
    </social>
    <social>
      <site>twitter</site>
      <handle>jwort1</handle>
      <address>https://theguardian.com/orci/nullam/molestie/nibh/in/lectus/pellentesque.json</address>
    </social>
  </socials>
  <memberships>
    <membership>
      <list>list5</list>
      <important>true</important>
      <ts>2021-09-14</ts>
    </membership>
    <membership>
      <list>list12</list>
      <important>true</important>
      <ts>2021-12-24</ts>
    </membership>
    <membership>
      <list>list12</list>
      <important>false</important>
      <ts>2021-10-09</ts>
    </membership>
  </memberships>
  <links>
    <link>
      <label>Quick View</label>
      <url>http://godaddy.com</url>
      <icon>faEye</icon>
    </link>
    <link>
      <label>Nomination History</label>
      <url>https://livejournal.com</url>
      <icon>faMedal</icon>
    </link>
    <link>
      <label>Comments</label>
      <url>http://youtube.com</url>
      <icon>faComments</icon>
    </link>
  </links>
<actions>
  <action>
    <url>http://oaic.gov.au</url>
    <icon>faCog</icon>
  </action>
  <action>
    <url>https://multiply.com</url>
    <icon>faCode</icon>
  </action>
  <action>
    <url>http://addthis.com</url>
    <icon>faSync</icon>
  </action>
</actions>
</person>