{
  "batchSize": 1,
  "sourceDatabase": "data-hub-FINAL",
  "targetDatabase": "data-hub-FINAL",
  "permissions": "data-hub-common,read,data-hub-common,update",
  "targetEntityType": "Emergency_Services",
  "sourceQuery": "cts.collectionQuery(['match_Emergency_Services'])",
  "provenanceGranularityLevel": "off",
  "collections": [
    "merge_Emergency_Services"
  ],
  "targetFormat": "json",
  "mergeRules": [
    {
      "entityPropertyPath": "Area_ID",
      "mergeType": "property-specific",
      "maxSources": "All",
      "maxValues": "All",
      "priorityOrder": {
        "sources": [ ],
        "timeWeight": 0
      }
    }
  ],
  "mergeStrategies": [ ],
  "targetCollections": null,
  "name": "merge_Emergency_Services",
  "description": "",
  "collection": [
    "match_Emergency_Services"
  ],
  "selectedSource": "collection",
  "timestamp": "",
  "additionalCollections": [ ],
  "headers": { },
  "interceptors": [ ],
  "customHook": { },
  "stepDefinitionName": "default-merging",
  "stepDefinitionType": "merging",
  "stepId": "merge_Emergency_Services-merging",
  "acceptsBatch": false,
  "stepUpdate": false,
  "lastUpdated": "2022-07-20T22:05:21.075496-07:00"
}