{
  "info": {
    "title": "Car_Services_NS_XML",
    "draft": false,
    "version": "1.0.0",
    "baseUri": "http://example.org/"
  },
  "definitions": {
    "Car_Services_NS_XML": {
      "properties": {
        "Area_ID": {
          "datatype": "integer",
          "facetable": false,
          "sortable": false,
          "collation": "http://marklogic.com/collation/codepoint"
        },
        "Name": {
          "datatype": "string",
          "facetable": false,
          "sortable": false,
          "collation": "http://marklogic.com/collation/codepoint"
        },
        "Rating": {
          "datatype": "decimal",
          "facetable": false,
          "sortable": false,
          "collation": "http://marklogic.com/collation/codepoint"
        },
        "LocatedIn": {
          "datatype": "integer",
          "relatedEntityType": "http://example.org/USZips-1.0.0/USZips",
          "joinPropertyName": "Area_ID"
        }
      },
      "namespace": "http://carservices.com/",
      "namespacePrefix": "crvs",
      "description": "Car Services area wise in US"
    }
  }
}