{"id":2025, "kind":"Bug", "createdAt":"2005-08-02T15:39:57.898234-07:00", "status":"Closed", "title":"idiv on atomized nodes fails with invalid expression error", "category":"Conformance", "severity":"Major", "priority":{"level":"5", "title":""}, "submittedBy":{"username":"mary", "name":"Mary Holstege", "email":"mary@cerisent.com"}, "assignTo":{"username":"nobody", "name":"nobody nobody", "email":"nobody@marklogic.com"}, "description":"<a> 1 </a> idiv <b> 2 </b>\n\nXDMP-EXPR: xdt:untypedAtomic(\" 1 \") idiv xs:double(\"2\") -- Invalid expression\n\nIt should work.\n\nNote that div (vs idiv) does work properly.", "samplequery":"", "sampledata":"", "version":"3.0-1", "tofixin":"3.0-3", "fixedin":"3.0-3", "platform":"windows", "memory":"", "processors":"", "note":"", "subscribers":[{"username":"mary", "name":"Mary Holstege", "email":"mary@cerisent.com"}], "attachments":[], "clones":[], "cloneOf":"", "support":{"headline":"idiv operator fails with untyped node arguments", "supportDescription":"The idiv operator fails with an XDMP-EXPR Invalid Expression error when operating on untyped nodes.  For instance, <a>1</a> idiv <b>2</b> will thow an error.", "publishStatus":"Publish", "tickets":[], "customerImpact":{"level":"N/A", "title":""}, "workaround":"Cast the arguments of idiv to xs:integer()."}, "tags":["Conformance", "mary"], "changeHistory":[{"time":"2005-08-10T15:34:21.99798-07:00", "updatedBy":{"username":"cjl", "name":"Christopher Lindblad", "email":"cjl@cerisent.com"}, "change":{"status":{"from":"", "to":"Fix"}, "assignTo":{"from":{"username":"cjl", "name":"Christopher Lindblad", "email":"cjl@cerisent.com"}, "to":{"username":"cjl", "name":"Christopher Lindblad", "email":"cjl@cerisent.com"}}}, "files":[], "show":true, "comment":"fix"}, {"time":"2005-08-11T15:43:12.057945-07:00", "updatedBy":{"username":"cjl", "name":"Christopher Lindblad", "email":"cjl@cerisent.com"}, "change":{"status":{"from":"", "to":"Test"}, "assignTo":{"from":{"username":"cjl", "name":"Christopher Lindblad", "email":"cjl@cerisent.com"}, "to":{"username":"rwang", "name":"Rachel Link", "email":"rwang@cerisent.com"}}}, "files":[], "show":true, "comment":"Fixed in 3.0-20050812\nand in 3.1-20050812\nSee also bug 2041"}, {"time":"2005-08-16T10:19:21.653787-07:00", "updatedBy":{"username":"rwang", "name":"Rachel Link", "email":"rwang@cerisent.com"}, "change":{"status":{"from":"", "to":"Ship"}, "assignTo":{"from":{"username":"rwang", "name":"Rachel Link", "email":"rwang@cerisent.com"}, "to":{"username":"nobody", "name":"nobody nobody", "email":"nobody@marklogic.com"}}}, "files":[], "show":true, "comment":"verified on build 0816. "}], "updatedAt":"2005-08-16T10:19:21.653787-07:00", "fixedAt":"2005-08-11T15:43:12.057945-07:00", "fixedBy":{"username":"cjl", "name":"Christopher Lindblad", "email":"cjl@cerisent.com"}, "shippedAt":"2005-08-16T10:19:21.653787-07:00", "shippedBy":{"username":"rwang", "name":"Rachel Link", "email":"rwang@cerisent.com"}, "renderDescriptionAs":"normal"}