<?xml version="1.0" encoding="UTF-8" standalone="yes"?>
<person>
  <personId>10011</personId>
  <nameGroup>
    <givenname>
      <value>Franz</value>
    </givenname>
    <surname>
      <value>Whaley</value>
    </surname>
    <fullname>
      <classification>C</classification>
      <restricted>true</restricted>
      <value>Whaley Franz</value>
      <source>
        <name>New York Times</name>
        <ts>2020-01-07T02:44:38Z</ts>
      </source>
      <source>
        <name>Washington Post</name>
        <ts>2012-01-09T14:22:09Z</ts>
      </source>
    </fullname>
  </nameGroup>
  <emails>
    <email>
      <value>vrobart0@hubpages.com</value>
      <classification>S</classification>
      <restricted>false</restricted>
    </email>
    <email>
      <value>jdagnall1@cloudflare.com</value>
      <classification>C</classification>
      <restricted>false</restricted>
    </email>
    <email>
      <value>lduckett2@google.pl</value>
      <classification>C</classification>
      <restricted>false</restricted>
    </email>
  </emails>
  <phone>458-125-5667</phone>
  <ssn>
    <value>387-45-6102</value>
    <restricted>true</restricted>
  </ssn>
  <images>
    <image>
      <url>https://cdn1.marklogic.com/wp-content/uploads/2021/07/chuck-hollis.jpeg</url>
      <source>
        <name>Wall Street Journal</name>
        <ts>2020-07-31T23:17:42Z</ts>
        <uploadedBy>bsmallsman0</uploadedBy>
      </source>
    </image>
    <image>
      <url>https://cdn1.marklogic.com/wp-content/uploads/2018/01/Diane-Burley-MarkLogic-2015.jpg</url>
      <source>
        <name>Wall Street Journal</name>
        <ts>2019-05-24T23:11:46Z</ts>
        <uploadedBy/>
      </source>
    </image>
  </images>
  <addresses>
    <address>
      <street>2 Susan Court</street>
      <city>Silver Spring</city>
      <state>MD</state>
      <postal>20904</postal>
      <country>United States</country>
      <latitude>39.0668</latitude>
      <longitude>-76.9969</longitude>
    </address>
    <address>
      <street>842 Hovde Point</street>
      <city>Indianapolis</city>
      <state>IN</state>
      <postal>46207</postal>
      <country>United States</country>
      <latitude>39.7673</latitude>
      <longitude>-86.1606</longitude>
    </address>
    <address>
      <street>72300 Fordem Alley</street>
      <city>Columbus</city>
      <state>OH</state>
      <postal>43268</postal>
      <country>United States</country>
      <latitude>39.969</latitude>
      <longitude>-83.0114</longitude>
    </address>
  </addresses>
  <schools>
    <school>
      <country>United States</country>
      <name>Polytechnic University, Westchester Graduate Center</name>
      <city>Lynn</city>
      <state>MA</state>
      <postal>01905</postal>
      <latitude>42.4678076</latitude>
      <longitude>-70.9844</longitude>
    </school>
    <school>
      <country>Canada</country>
      <name>Mount Royal College</name>
      <city>Sainte-Marthe-sur-le-Lac</city>
      <state>QC</state>
      <postal>H9K</postal>
      <latitude>45.4574274</latitude>
      <longitude>-73.9157063</longitude>
    </school>
  </schools>
  <status>Active</status>
  <sources>
    <source>
      <name>New York Times</name>
      <ts>2011-12-08T21:56:20Z</ts>
    </source>
  </sources>
  <sources>
    <source>
      <name>Los Angeles Times</name>
      <ts>2021-11-14T12:26:44Z</ts>
    </source>
  </sources>
  <sources>
    <source>
      <name>New York Times</name>
      <ts>2021-04-15T01:15:35Z</ts>
    </source>
  </sources>
  <relations>
    <relation>
      <id>/person/10086.xml</id>
      <predicate>worksWith</predicate>
      <imageSrc>https://cdn1.marklogic.com/wp-content/uploads/2020/04/JamesKenwood-headshot-600x600-1.jpg</imageSrc>
      <fullname>Gwinn Philippine</fullname>
      <city>Wichita</city>
      <state>KS</state>
    </relation>
    <relation>
      <id>/person/10098.xml</id>
      <predicate>livesWith</predicate>
      <imageSrc>https://cdn1.marklogic.com/wp-content/uploads/2020/11/george-bloom-headshot-300x300-1.jpg</imageSrc>
      <fullname>Hawse Wilma</fullname>
      <city>Miami</city>
      <state>FL</state>
    </relation>
    <relation>
      <id>/person/10093.xml</id>
      <predicate>worksWith</predicate>
      <imageSrc>https://cdn1.marklogic.com/wp-content/uploads/2018/01/Alicia-Saia-MarkLogic1.jpg</imageSrc>
      <fullname>Winnett Grata</fullname>
      <city>Pittsburgh</city>
      <state>PA</state>
    </relation>
    <relation>
      <id>/person/10013.xml</id>
      <predicate>relatedTo</predicate>
      <imageSrc>https://cdn1.marklogic.com/wp-content/uploads/2018/02/trinh-lieu-profile.jpg</imageSrc>
      <fullname>Mc Cahey Craggy</fullname>
      <city>Knoxville</city>
      <state>TN</state>
    </relation>
    <relation>
      <id>/person/10071.xml</id>
      <predicate>livesWith</predicate>
      <imageSrc>https://cdn1.marklogic.com/wp-content/uploads/2018/01/headshot_square_286x286.jpg</imageSrc>
      <fullname>Dionis Zane</fullname>
      <city>Raleigh</city>
      <state>NC</state>
    </relation>
  </relations>
  <createdOn>
    <ts>2022-01-22T07:47:38Z</ts>
    <user>fwhaleya</user>
  </createdOn>
  <lastUpdated>
    <ts>2022-01-13T10:06:53Z</ts>
    <user>fwhaleya</user>
  </lastUpdated>
  <socials>
    <social>
      <site>linkedin</site>
      <handle>jsisnett0</handle>
      <address>https://google.it/consequat/metus/sapien/ut/nunc/vestibulum.png</address>
    </social>
    <social>
      <site>facebook</site>
      <handle>cshallow1</handle>
      <address>http://istockphoto.com/morbi/vel/lectus/in.json</address>
    </social>
    <social>
      <site>twitter</site>
      <handle>rmellon2</handle>
      <address>http://google.de/est/risus/auctor/sed/tristique.html</address>
    </social>
  </socials>
  <memberships>
    <membership>
      <list>list4</list>
      <important>false</important>
      <ts>2021-08-18</ts>
    </membership>
    <membership>
      <list>list2</list>
      <important>false</important>
      <ts>2021-10-26</ts>
    </membership>
    <membership>
      <list>list6</list>
      <important>true</important>
      <ts>2021-09-11</ts>
    </membership>
  </memberships>
  <links>
    <link>
      <label>Quick View</label>
      <url>https://ted.com</url>
      <icon>faEye</icon>
    </link>
    <link>
      <label>Nomination History</label>
      <url>https://freewebs.com</url>
      <icon>faMedal</icon>
    </link>
    <link>
      <label>Comments</label>
      <url>http://examiner.com</url>
      <icon>faComments</icon>
    </link>
  </links>
<actions>
  <action>
    <url>http://oaic.gov.au</url>
    <icon>faCog</icon>
  </action>
  <action>
    <url>https://multiply.com</url>
    <icon>faCode</icon>
  </action>
  <action>
    <url>http://addthis.com</url>
    <icon>faSync</icon>
  </action>
</actions>
</person>