<?xml version="1.0" encoding="UTF-8" standalone="yes"?>
<person>
  <personId>10044</personId>
  <nameGroup>
    <givenname>
      <value>Nikkie</value>
    </givenname>
    <surname>
      <value>Smart</value>
    </surname>
    <fullname>
      <classification>C</classification>
      <restricted>true</restricted>
      <value>Smart Nikkie</value>
      <source>
        <name>Chicago Tribune</name>
        <ts>2011-01-09T03:59:11Z</ts>
      </source>
    </fullname>
  </nameGroup>
  <emails>
    <email>
      <value>khovell0@phpbb.com</value>
      <classification>S</classification>
      <restricted>false</restricted>
    </email>
  </emails>
  <phone>531-723-3892</phone>
  <ssn>
    <value>399-84-4474</value>
    <classification>(S)</classification>
  </ssn>
  <images>
    <image>
      <url>https://cdn1.marklogic.com/wp-content/uploads/2018/01/headshot_square_286x286.jpg</url>
      <source>
        <name>Los Angeles Times</name>
        <ts>2011-11-27T16:17:39Z</ts>
        <uploadedBy>egommery0</uploadedBy>
      </source>
    </image>
  </images>
  <addresses>
    <address>
      <street>30026 Mayfield Drive</street>
      <city>Trenton</city>
      <state>NJ</state>
      <postal>08638</postal>
      <country>United States</country>
      <latitude>40.251</latitude>
      <longitude>-74.7627</longitude>
    </address>
    <address>
      <street>65 Mcguire Point</street>
      <city>Knoxville</city>
      <state>TN</state>
      <postal>37931</postal>
      <country>United States</country>
      <latitude>35.9924</latitude>
      <longitude>-84.1201</longitude>
    </address>
  </addresses>
  <schools>
    <school>
      <country>United States</country>
      <name>St. Peter's College</name>
      <city>Columbus</city>
      <state>OH</state>
      <postal>43268</postal>
      <latitude>39.96</latitude>
      <longitude>-83</longitude>
      <source>
        <name>USA Today</name>
        <ts>2011-09-14T09:23:37Z</ts>
      </source>
      <source>
        <name>New York Times</name>
        <ts>2011-02-19T15:43:40Z</ts>
      </source>
      <source>
        <name>Chicago Tribune</name>
        <ts>2020-06-12T17:26:29Z</ts>
      </source>
    </school>
    <school>
      <country>Mexico</country>
      <name>Instituto Tecnológico de San Luis Potosí</name>
      <city>Libertad</city>
      <state>SON</state>
      <postal>83450</postal>
      <latitude>19.4779768</latitude>
      <longitude>-99.1771001</longitude>
      <source>
        <name>USA Today</name>
        <ts>2015-05-01T15:27:42Z</ts>
      </source>
    </school>
  </schools>
  <status>Active</status>
  <sources>
    <source>
      <name>New York Times</name>
      <ts>2017-10-02T09:00:30Z</ts>
    </source>
  </sources>
  <sources>
    <source>
      <name>Los Angeles Times</name>
      <ts>2017-03-07T12:57:45Z</ts>
    </source>
  </sources>
  <sources>
    <source>
      <name>Wall Street Journal</name>
      <ts>2011-06-20T15:18:49Z</ts>
    </source>
  </sources>
  <relations>
    <relation>
      <id>/person/10010.xml</id>
      <predicate>livesWith</predicate>
      <imageSrc>https://cdn1.marklogic.com/wp-content/uploads/2018/01/Michael-Malgeri-MarkLogic.jpg</imageSrc>
      <fullname>McCorkindale Humfrey</fullname>
      <city>Columbia</city>
      <state>SC</state>
    </relation>
    <relation>
      <id>/person/10078.xml</id>
      <predicate>livesWith</predicate>
      <imageSrc>https://cdn1.marklogic.com/wp-content/uploads/2018/01/Diane-Burley-MarkLogic-2015.jpg</imageSrc>
      <fullname>Jonah Alyce</fullname>
      <city>San Antonio</city>
      <state>TX</state>
    </relation>
    <relation>
      <id>/person/10025.xml</id>
      <predicate>relatedTo</predicate>
      <imageSrc>https://cdn1.marklogic.com/wp-content/uploads/2020/11/george-bloom-headshot-300x300-1.jpg</imageSrc>
      <fullname>Mc Carroll Izak</fullname>
      <city>Cumming</city>
      <state>GA</state>
    </relation>
    <relation>
      <id>/person/10100.xml</id>
      <predicate>worksWith</predicate>
      <imageSrc>https://cdn1.marklogic.com/wp-content/uploads/2018/01/Diane-Burley-MarkLogic-2015.jpg</imageSrc>
      <fullname>Inott Emili</fullname>
      <city>Lexington</city>
      <state>KY</state>
    </relation>
    <relation>
      <id>/person/10001.xml</id>
      <predicate>relatedTo</predicate>
      <imageSrc>https://cdn1.marklogic.com/wp-content/uploads/2018/01/Diane-Burley-MarkLogic-2015.jpg</imageSrc>
      <fullname>Preator Vivi</fullname>
      <city>Newport Beach</city>
      <state>CA</state>
    </relation>
  </relations>
  <createdOn>
    <ts>2022-02-07T12:16:26Z</ts>
    <user>nsmart17</user>
  </createdOn>
  <lastUpdated>
    <ts>2022-02-08T02:10:58Z</ts>
    <user>nsmart17</user>
  </lastUpdated>
  <socials>
    <social>
      <site>facebook</site>
      <handle/>
      <address>https://harvard.edu/justo/in.aspx</address>
    </social>
    <social>
      <site>linkedin</site>
      <handle>plosemann1</handle>
      <address>http://youtube.com/donec/vitae/nisi/nam/ultrices/libero.jsp</address>
    </social>
  </socials>
  <memberships/>
  <links>
    <link>
      <label>Quick View</label>
      <url>http://archive.org</url>
      <icon>fa-eye</icon>
    </link>
    <link>
      <label>Nomination History</label>
      <url>http://prlog.org</url>
      <icon>fa-medal</icon>
    </link>
    <link>
      <label>Comments</label>
      <url>https://ucla.edu</url>
      <icon>fa-comments</icon>
    </link>
  </links>
  <activities>
    <activity>
      <predicate>transferredTo</predicate>
      <place>Viva</place>
      <source>
        <name>USA Today</name>
        <ts>2010-10-25T17:51:17Z</ts>
        <createdBy>Sephira Chishull</createdBy>
        <approvedBy>Guglielmo Nornable</approvedBy>
      </source>
    </activity>
    <activity>
      <predicate>endedAt</predicate>
      <place>Aimbo</place>
      <source>
        <name>New York Times</name>
        <ts>2012-11-22T17:10:34Z</ts>
        <createdBy>Breanne Dewes</createdBy>
        <approvedBy>Lorie Sidebotton</approvedBy>
      </source>
    </activity>
    <activity>
      <predicate>movedTo</predicate>
      <place>Muxo</place>
      <source>
        <name>Chicago Tribune</name>
        <ts>2014-12-16T14:51:55Z</ts>
        <createdBy>Carolus Sentinella</createdBy>
        <approvedBy>Haze Bambra</approvedBy>
      </source>
    </activity>
    <activity>
      <predicate>movedTo</predicate>
      <place>Brightdog</place>
      <source>
        <name>Los Angeles Times</name>
        <ts>2012-11-16T10:41:15Z</ts>
        <createdBy>Madlen Spuffard</createdBy>
        <approvedBy>Dory Klishin</approvedBy>
      </source>
    </activity>
  </activities>
</person>