{
    "eventid": "199311230001",
    "iyear": "1993",
    "imonth": "11",
    "iday": "23",
    "extended": "0",
    "country": "182",
    "country_txt": "Somalia",
    "region": "11",
    "region_txt": "Sub-Saharan Africa",
    "provstate": "Banaadir (Region)",
    "city": "Mogadishu",
    "vicinity": "0",
    "summary": "11/23/1993: Unknown gunmen attacked an United Nations convoy of relief workers in Mogadishu. No fatalities and 3 injured.",
    "crit1": "1",
    "crit2": "1",
    "crit3": "1",
    "doubtterr": "0",
    "multiple": "0",
    "success": "1",
    "suicide": "0",
    "attacktype1": "2",
    "attacktype1_txt": "Armed Assault",
    "targtype1": "13",
    "targtype1_txt": "Other",
    "corp1": "United Nations",
    "target1": "A convoy of relief workers",
    "natlty1": "999",
    "natlty1_txt": "Multinational",
    "gname": "Unknown",
    "motive": "Unknown",
    "guncertain1": "0",
    "individual": "0",
    "nperps": "4",
    "nperpcap": "0",
    "claimed": "0",
    "compclaim": "-9",
    "weaptype1": "5",
    "weaptype1_txt": "Firearms",
    "weapsubtype1": "5",
    "weapsubtype1_txt": "Unknown Gun Type",
    "nkill": "0",
    "nkillus": "0",
    "nkillter": "0",
    "nwound": "3",
    "nwoundus": "1",
    "nwoundte": "0",
    "property": "-9",
    "propextent": "4",
    "propextent_txt": "Unknown",
    "ishostkid": "0",
    "addnotes": "The identities or affiliations of the gunmen were not known. The American, Debbie Owen, was slightly wounded.  Two other Somali guards were also wounded.",
    "scite1": "Edward F. Mickolus, Terrorism, 1992-1995: A Chronology of Events and a Selectively Annotated Bibliography, Westport, CT: Greenwood Press, 1997.",
    "dbsource": "CETIS",
    "INT_LOG": "-9",
    "INT_IDEO": "-9",
    "INT_MISC": "1",
    "INT_ANY": "1"
}